SiLibUSB/__init__.py
SiLibUSB/siusbdevice.py
pySiLibUSB-3.0.2.dist-info/METADATA
pySiLibUSB-3.0.2.dist-info/WHEEL
pySiLibUSB-3.0.2.dist-info/top_level.txt
pySiLibUSB-3.0.2.dist-info/RECORD
