Metadata-Version: 2.1
Name: pySiLibUSB
Version: 3.0.2
Summary: pySiLibUSB - SILAB USB device application programming interface
Home-page: https://github.com/SiLab-Bonn/pySiLibUSB
Author: Tomasz Hemperek, Jens Janssen
Author-email: hemperek@uni-bonn.de, janssen@physik.uni-bonn.de
Maintainer: Tomasz Hemperek, Jens Janssen
Maintainer-email: hemperek@uni-bonn.de, janssen@physik.uni-bonn.de
License: BSD 3-Clause ("BSD New" or "BSD Simplified") License
Platform: any
Requires-Python: >=2.7
Requires-Dist: pyusb (>=1.0.0rc1)
